gdcli/__init__.py
gdcli/gd.py
gdcli/commands/__init__.py
gdcli/commands/cli.py
gdcli/commands/options.py
gdcli/helpers/__init__.py
gdcli/helpers/browser.py
gdcli/utils/__init__.py
gdcli/utils/cli_arguments/__init__.py
gdcli/utils/cli_arguments/args.py
gdcli/utils/query/__init__.py
gdcli/utils/query/builder.py
gdcli/utils/query/select.py
gdcli-1.1.9.dist-info/LICENSE
gdcli-1.1.9.dist-info/METADATA
gdcli-1.1.9.dist-info/WHEEL
gdcli-1.1.9.dist-info/entry_points.txt
gdcli-1.1.9.dist-info/top_level.txt
gdcli-1.1.9.dist-info/RECORD
