Metadata-Version: 2.1
Name: gdcli
Version: 1.1.9
Summary: 
Home-page: https://github.com/hegade
Author: Subrahmanya s hegade
Author-email: hegadedevelopment@gmail.com
License: UNKNOWN
Keywords: google dorks,cli,advanced google search
Platform: UNKNOWN
